pdll/__init__.py
pdll/_pairwise.py
pdll-0.3.1.dist-info/LICENSE
pdll-0.3.1.dist-info/METADATA
pdll-0.3.1.dist-info/WHEEL
pdll-0.3.1.dist-info/top_level.txt
pdll-0.3.1.dist-info/RECORD
