Metadata-Version: 2.1
Name: pdll
Version: 0.3.1
Summary: Pairwise difference learning library is a scikit learn compatible library for learning from pairwise differences.
Author: Mohamed Karim Belaid
Author-email: karim.belaid@idiada.com
License: Apache-2.0
Project-URL: Tracker, https://github.com/Karim-53/pdll/issues
Project-URL: Source, https://github.com/Karim-53/pdll
Classifier: Development Status :: 3 - Alpha
Classifier: Intended Audience :: Developers
Classifier: Intended Audience :: Education
Classifier: Intended Audience :: Science/Research
Classifier: Topic :: Software Development :: Libraries :: Python Modules
Classifier: Topic :: Scientific/Engineering :: Artificial Intelligence
Classifier: License :: OSI Approved :: Apache Software License
Classifier: Programming Language :: Python :: 3
Classifier: Operating System :: OS Independent
License-File: LICENSE
Requires-Dist: numpy
Requires-Dist: pandas
Requires-Dist: scikit-learn
Requires-Dist: setuptools
